cfonts/__init__.py
cfonts/__version__.py
cfonts/cli.py
cfonts/colors.py
cfonts/consts.py
cfonts/core.py
cfonts/fonts/3d.json
cfonts/fonts/block.json
cfonts/fonts/chrome.json
cfonts/fonts/grid.json
cfonts/fonts/huge.json
cfonts/fonts/pallet.json
cfonts/fonts/shade.json
cfonts/fonts/simple.json
cfonts/fonts/simple3d.json
cfonts/fonts/simpleBlock.json
cfonts/fonts/slick.json
cfonts/fonts/tiny.json
cfonts/py.typed
cfonts-1.5.2.dist-info/entry_points.txt
cfonts-1.5.2.dist-info/WHEEL
cfonts-1.5.2.dist-info/METADATA
cfonts-1.5.2.dist-info/licenses/LICENSE
cfonts-1.5.2.dist-info/RECORD
