Metadata-Version: 2.1
Name: cfonts
Version: 1.5.2
Summary: Sexy fonts for the console
License: MIT
Author-email: ZULFIQOR MAMADALIYEV <zulfiqorjonmamadaliev@gmail.com>
Requires-Python: >=3.6
Classifier: Development Status :: 4 - Beta
Classifier: License :: OSI Approved :: MIT License
Classifier: Programming Language :: Python :: Implementation :: CPython
Classifier: Programming Language :: Python :: Implementation :: PyPy
Requires-Dist: colorama
Project-URL: Documentation, https://python-cfonts.readthedocs.io/
Project-URL: homepage, https://github.com/frostming/python-cfonts
